unifi_api/__init__.py
unifi_api/api.py
unifi_api/base_api.py
unifi_api/utils/__init__.py
unifi_api/utils/decorators.py
unifi_api/utils/exceptions.py
unifi_api/utils/models.py
unifi_python_api-0.2.3.dist-info/LICENSE
unifi_python_api-0.2.3.dist-info/METADATA
unifi_python_api-0.2.3.dist-info/WHEEL
unifi_python_api-0.2.3.dist-info/top_level.txt
unifi_python_api-0.2.3.dist-info/RECORD
