Metadata-Version: 2.1
Name: unifi-python-api
Version: 0.2.3
Summary: A small example package
Author-email: André Carneiro <acarneiro.dev@gmail.com>
Project-URL: Homepage, https://github.com/r4mmer/unifi_python_api
Project-URL: Issues, https://github.com/r4mmer/unifi_python_api/issues
Classifier: Programming Language :: Python :: 3
Classifier: Operating System :: OS Independent
Classifier: Development Status :: 3 - Alpha
Classifier: Intended Audience :: Information Technology
Classifier: Topic :: Software Development :: Libraries :: Python Modules
Classifier: Topic :: Utilities
Requires-Python: >=3.8
License-File: LICENSE
Requires-Dist: requests <3,>=2.32.0
Requires-Dist: trafaret <3,>=2.1.1
